{
  "main": {
    "id": "4720f684171f4023",
    "type": "split",
    "children": [
      {
        "id": "266ee69a0e061868",
        "type": "tabs",
        "children": [
          {
            "id": "8f5298195f3dc4d8",
            "type": "leaf",
            "state": {
              "type": "markdown",
              "state": {
                "file": "Untitled.md",
                "mode": "source",
                "source": false
              },
              "icon": "lucide-file",
              "title": "Untitled"
            }
          }
        ]
      }
    ],
    "direction": "vertical"
  },
  "left": {
    "id": "8ae12b35fe9ad7ab",
    "type": "split",
    "children": [
      {
        "id": "4b1f9f3cf7f5908f",
        "type": "tabs",
        "children": [
          {
            "id": "06d089e299955857",
            "type": "leaf",
            "state": {
              "type": "file-explorer",
              "state": {
                "sortOrder": "alphabetical",
                "autoReveal": false
              },
              "icon": "lucide-folder-closed",
              "title": "Files"
            }
          },
          {
            "id": "3d3cafb9fdba797e",
            "type": "leaf",
            "state": {
              "type": "search",
              "state": {
                "query": "",
                "matchingCase": false,
                "explainSearch": false,
                "collapseAll": false,
                "extraContext": false,
                "sortOrder": "alphabetical"
              },
              "icon": "lucide-search",
              "title": "Search"
            }
          },
          {
            "id": "0a88d0179b304216",
            "type": "leaf",
            "state": {
              "type": "bookmarks",
              "state": {},
              "icon": "lucide-bookmark",
              "title": "Bookmarks"
            }
          }
        ]
      }
    ],
    "direction": "horizontal",
    "width": 300,
    "collapsed": true
  },
  "right": {
    "id": "36e6efc85ec31b9b",
    "type": "split",
    "children": [
      {
        "id": "4b1bd875833cd46c",
        "type": "tabs",
        "children": [
          {
            "id": "72e1b2c170624d27",
            "type": "leaf",
            "state": {
              "type": "backlink",
              "state": {
                "file": "Untitled.md",
                "collapseAll": false,
                "extraContext": false,
                "sortOrder": "alphabetical",
                "showSearch": false,
                "searchQuery": "",
                "backlinkCollapsed": false,
                "unlinkedCollapsed": true
              },
              "icon": "links-coming-in",
              "title": "Backlinks for Untitled"
            }
          },
          {
            "id": "4054e7abf85d1924",
            "type": "leaf",
            "state": {
              "type": "outgoing-link",
              "state": {
                "file": "Untitled.md",
                "linksCollapsed": false,
                "unlinkedCollapsed": true
              },
              "icon": "links-going-out",
              "title": "Outgoing links from Untitled"
            }
          },
          {
            "id": "41880d90cbbe579e",
            "type": "leaf",
            "state": {
              "type": "tag",
              "state": {
                "sortOrder": "frequency",
                "useHierarchy": true,
                "showSearch": false,
                "searchQuery": ""
              },
              "icon": "lucide-tags",
              "title": "Tags"
            }
          },
          {
            "id": "6264877c4beab809",
            "type": "leaf",
            "state": {
              "type": "outline",
              "state": {
                "file": "Untitled.md",
                "followCursor": false,
                "showSearch": false,
                "searchQuery": ""
              },
              "icon": "lucide-list",
              "title": "Outline of Untitled"
            }
          },
          {
            "id": "23f499ce120f448d",
            "type": "leaf",
            "state": {
              "type": "git-view",
              "state": {},
              "icon": "git-pull-request",
              "title": "Source Control"
            }
          }
        ],
        "currentTab": 4
      }
    ],
    "direction": "horizontal",
    "width": 300
  },
  "left-ribbon": {
    "hiddenItems": {
      "switcher:Open quick switcher": false,
      "graph:Open graph view": false,
      "canvas:Create new canvas": false,
      "daily-notes:Open today's daily note": false,
      "templates:Insert template": false,
      "command-palette:Open command palette": false,
      "obsidian-git:Open Git source control": false
    }
  },
  "active": "6264877c4beab809",
  "lastOpenFiles": [
    "Untitled.md",
    "Welcome.md"
  ]
}